{
  "$schema": "https://wails.io/schemas/config.v2.json",
  "name": "AETHEL",
  "outputfilename": "AETHEL",
  "frontend": {
    "dir": "frontend",
    "install": "",
    "build": "",
    "dev": { "watcher": "" },
    "devServer": ""
  },
  "author": { "name": "VGT", "email": "" },
  "info": {
    "companyName": "VGT",
    "productName": "VGT AETHEL",
    "productVersion": "1.0.0-beta.2",
    "copyright": "2026 VGT",
    "comments": "AETHEL Beta V2 - Sovereign Personal Intelligence OS · Production Candidate"
  }
}
